odoo/addons/purchase_requisition_auto_rfq/README.rst
odoo/addons/purchase_requisition_auto_rfq/__init__.py
odoo/addons/purchase_requisition_auto_rfq/__manifest__.py
odoo/addons/purchase_requisition_auto_rfq/demo/product_product.xml
odoo/addons/purchase_requisition_auto_rfq/i18n/fr.po
odoo/addons/purchase_requisition_auto_rfq/i18n/purchase_requisition_auto_rfq.pot
odoo/addons/purchase_requisition_auto_rfq/models/__init__.py
odoo/addons/purchase_requisition_auto_rfq/models/purchase_requisition.py
odoo/addons/purchase_requisition_auto_rfq/readme/CONTRIBUTORS.rst
odoo/addons/purchase_requisition_auto_rfq/readme/DESCRIPTION.rst
odoo/addons/purchase_requisition_auto_rfq/readme/USAGE.rst
odoo/addons/purchase_requisition_auto_rfq/static/description/icon.png
odoo/addons/purchase_requisition_auto_rfq/static/description/index.html
odoo/addons/purchase_requisition_auto_rfq/tests/__init__.py
odoo/addons/purchase_requisition_auto_rfq/tests/test_purchase_requisition.py
odoo/addons/purchase_requisition_auto_rfq/view/purchase_requisition.xml
odoo12_addon_purchase_requisition_auto_rfq-12.0.2.0.0.99.dev3.dist-info/METADATA
odoo12_addon_purchase_requisition_auto_rfq-12.0.2.0.0.99.dev3.dist-info/WHEEL
odoo12_addon_purchase_requisition_auto_rfq-12.0.2.0.0.99.dev3.dist-info/top_level.txt
odoo12_addon_purchase_requisition_auto_rfq-12.0.2.0.0.99.dev3.dist-info/RECORD
